pypackage/__init__.py
pypackage/classified.py
pypackage/classifiers
pypackage/cleaner.py
pypackage/cmdline.py
pypackage/commands.py
pypackage/config.py
pypackage/configure.py
pypackage/constants.py
pypackage/context.py
pypackage/guessing.py
pypackage/runner.py
pypackage-0.2.6.dist-info/DESCRIPTION.rst
pypackage-0.2.6.dist-info/METADATA
pypackage-0.2.6.dist-info/RECORD
pypackage-0.2.6.dist-info/WHEEL
pypackage-0.2.6.dist-info/entry_points.txt
pypackage-0.2.6.dist-info/metadata.json
pypackage-0.2.6.dist-info/top_level.txt
