Metadata-Version: 2.0
Name: pypackage
Version: 0.2.6
Summary: Pypackage looks to package python without writing a setup.py
Home-page: http://ccpgames.github.io/pypackage
Author: Adam Talsma
Author-email: se-adam.talsma@ccpgames.com
License: UNKNOWN
Download-URL: https://github.com/ccpgames/pypackage
Platform: UNKNOWN
Classifier: Development Status :: 4 - Beta
Classifier: Environment :: Console
Classifier: Environment :: Console :: Curses
Classifier: Intended Audience :: Developers
Classifier: Intended Audience :: System Administrators
Classifier: License :: OSI Approved :: MIT License
Classifier: Operating System :: OS Independent
Classifier: Programming Language :: Python :: 2.7
Classifier: Programming Language :: Python :: 3
Classifier: Programming Language :: Python :: 3.4
Classifier: Topic :: Software Development
Classifier: Topic :: Software Development :: Code Generators
Classifier: Topic :: System :: Archiving :: Packaging
Classifier: Topic :: System :: Installation/Setup
Classifier: Topic :: System :: Software Distribution
Classifier: Topic :: Utilities
Requires-Dist: PyYAML (>=3.0)
Requires-Dist: nose (>=1.3.0)
Requires-Dist: pytest (>=2.7.0)
Requires-Dist: setuptools (>=15.0)
Requires-Dist: wheel (>=0.24.0)
